{"schema":"opendota-public-hero-v4","hero":"dazzle","hero_id":50,"meta":{"matches":776,"records":776,"date_min":"2026-07-15","date_max":"2026-07-17","cohorts":{"pure_immortal":{"label":"纯冠绝","matches":459,"records":459},"immortal_divine":{"label":"冠绝＋超凡","matches":317,"records":317}}},"dictionaries":{"d":["2026-07-15","2026-07-16","2026-07-17"],"p":["7.41"],"item":["item_aegis","item_aeon_disk","item_aether_lens","item_ancient_janggo","item_arcane_blink","item_arcane_boots","item_assault","item_black_king_bar","item_blade_mail","item_blade_of_alacrity","item_blight_stone","item_blink","item_blood_grenade","item_bloodthorn","item_boots","item_boots_of_bearing","item_bottle","item_bracer","item_branches","item_buckler","item_chainmail","item_cheese","item_circlet","item_clarity","item_cloak","item_consecrated_wraps","item_crellas_crozier","item_crown","item_cyclone","item_desolator","item_diffusal_blade","item_dust","item_enchanted_mango","item_energy_booster","item_essence_distiller","item_ethereal_blade","item_faerie_fire","item_falcon_blade","item_famango","item_flask","item_fluffy_hat","item_foragers_health","item_foragers_mana","item_foragers_stats","item_force_staff","item_gauntlets","item_gem","item_ghost","item_glimmer_cape","item_gloves","item_great_famango","item_greater_crit","item_greater_famango","item_guardian_greaves","item_gungir","item_hand_of_midas","item_headdress","item_holy_locket","item_hurricane_pike","item_hydras_breath","item_hyperstone","item_infused_raindrop","item_lesser_crit","item_lotus_orb","item_mage_slayer","item_magic_stick","item_magic_wand","item_manta","item_mantle","item_mekansm","item_meteor_hammer","item_mjollnir","item_mystic_staff","item_null_talisman","item_nullifier","item_oblivion_staff","item_octarine_core","item_ogre_axe","item_orb_of_corrosion","item_orb_of_frost","item_orchid","item_pavise","item_pers","item_pipe","item_platemail","item_point_booster","item_power_treads","item_quelling_blade","item_radiance","item_recipe_aeon_disk","item_recipe_aether_lens","item_recipe_assault","item_recipe_cyclone","item_recipe_glimmer_cape","item_recipe_lotus_orb","item_recipe_octarine_core","item_recipe_pipe","item_ring_of_basilius","item_ring_of_protection","item_ring_of_tarrasque","item_rod_of_atos","item_roshans_banner","item_shadow_amulet","item_shawl","item_sheepstick","item_silver_edge","item_skadi","item_smoke_of_deceit","item_solar_crest","item_soul_booster","item_sphere","item_spirit_vessel","item_staff_of_wizardry","item_swift_blink","item_tango","item_tranquil_boots","item_travel_boots","item_ultimate_orb","item_ultimate_scepter","item_urn_of_shadows","item_vitality_booster","item_vladmir","item_void_stone","item_ward_dispenser","item_ward_observer","item_ward_sentry","item_wind_lace","item_wind_waker","item_witch_blade","item_wraith_band"]},"record_fields":["match_id","date","patch","player_slot","win","level","net_worth","duration","rank_tier","main_slots","backpack_slots","cohort_code"],"main_inventory_fields":["item_0","item_1","item_2","item_3","item_4","item_5"],"backpack_fields":["backpack_0","backpack_1","backpack_2"],"empty_item_index":-1,"cohort_codes":{"0":"pure_immortal","1":"immortal_divine"},"records":[[8897667985,0,0,3,0,14,9209,2028,80,[125,68,57,48,5,-1],[-1,-1,-1],1],[8897678629,0,0,129,0,11,6237,1671,80,[5,69,66,125,107,103],[102,-1,-1],0],[8897682700,0,0,2,1,14,9140,1464,74,[123,103,5,73,2,57],[-1,-1,-1],1],[8897688389,0,0,129,1,21,12542,2804,80,[44,48,123,5,31,1],[-1,-1,-1],0],[8897692038,0,0,2,1,21,11084,2327,80,[53,57,48,123,-1,31],[-1,-1,-1],0],[8897701747,0,0,2,0,15,7151,1894,80,[53,66,123,-1,107,79],[-1,-1,-1],0],[8897709590,0,0,130,1,22,12074,3710,80,[48,47,14,57,123,31],[87,-1,-1],1],[8897710321,0,0,2,1,18,11305,1972,80,[31,107,125,53,57,11],[-1,-1,-1],1],[8897716443,0,0,131,1,22,15632,2761,80,[11,31,34,-1,53,38],[107,-1,-1],0],[8897718829,0,0,128,1,18,11403,1828,80,[44,63,104,5,62,7],[107,66,11],0],[8897720630,0,0,2,0,6,3377,1357,80,[65,126,49,12,5,124],[-1,-1,-1],0],[8897721795,0,0,2,1,21,14510,2274,80,[48,53,10,66,118,126],[107,125,-1],0],[8897722261,0,0,128,0,16,7405,2449,80,[50,11,-1,10,57,14],[107,-1,38],0],[8897723324,0,0,3,1,17,9923,1966,80,[123,53,28,57,107,-1],[-1,-1,-1],0],[8897731574,0,0,132,1,18,9919,2087,75,[47,57,48,123,5,114],[-1,-1,-1],1],[8897733479,0,0,1,1,21,15311,2443,80,[11,28,57,53,-1,-1],[-1,-1,-1],0],[8897735552,0,0,128,0,14,8425,2188,80,[5,81,69,82,66,84],[-1,-1,-1],0],[8897742427,0,0,3,0,14,6868,1935,80,[48,124,66,5,-1,-1],[-1,-1,-1],1],[8897746150,0,0,4,1,13,7597,1373,80,[11,66,61,12,5,10],[-1,-1,-1],1],[8897749272,0,0,4,0,10,6024,1430,80,[102,66,55,103,5,-1],[-1,-1,-1],0],[8897752789,0,0,0,0,22,15905,2866,80,[53,57,126,125,76,48],[107,-1,-1],0],[8897753594,0,0,3,1,17,11430,2272,80,[53,57,123,47,31,-1],[-1,-1,-1],0],[8897755438,0,0,1,1,21,13756,2463,75,[53,17,57,-1,123,28],[107,31,-1],1],[8897757657,0,0,130,1,18,10407,2027,75,[119,-1,44,5,48,-1],[107,-1,-1],1],[8897757770,0,0,128,0,16,6879,2482,80,[31,48,11,5,107,66],[-1,-1,-1],0],[8897758788,0,0,2,1,28,16725,3718,80,[26,53,48,-1,31,57],[-1,-1,-1],0],[8897766363,0,0,130,0,17,9470,2135,80,[48,55,66,-1,53,123],[-1,-1,-1],0],[8897768843,0,0,130,0,20,11569,2293,80,[-1,118,53,73,-1,17],[107,-1,-1],1],[8897773521,0,0,2,0,25,14216,3435,80,[123,15,44,5,1,2],[107,31,-1],0],[8897774353,0,0,3,1,20,12766,2916,80,[82,123,48,53,2,120],[-1,-1,-1],0],[8897774835,0,0,2,0,17,8655,2345,80,[5,31,124,48,69,57],[-1,-1,-1],0],[8897778189,0,0,129,0,19,9476,2354,80,[48,-1,123,5,65,11],[107,-1,-1],0],[8897780666,0,0,3,1,15,10369,1743,80,[53,31,57,125,-1,107],[-1,-1,-1],0],[8897784780,0,0,0,0,19,8850,2463,80,[-1,47,53,36,123,126],[-1,-1,-1],0],[8897785437,0,0,1,1,24,17555,3226,80,[63,57,48,47,5,2],[-1,-1,125],0],[8897786039,0,0,0,0,15,7184,2146,73,[44,61,123,5,57,-1],[-1,-1,-1],1],[8897787940,0,0,129,1,26,24040,3150,80,[118,67,11,59,86,73],[-1,-1,-1],0],[8897788456,0,0,2,0,22,12194,2919,80,[53,47,66,107,79,118],[-1,-1,-1],0],[8897789770,0,0,2,1,22,13027,2795,80,[63,5,57,-1,126,44],[-1,-1,-1],0],[8897800178,0,0,2,1,15,9108,1644,75,[44,5,57,31,-1,79],[-1,-1,-1],1],[8897801208,0,0,1,0,21,14114,2241,80,[66,37,86,70,128,118],[-1,-1,-1],0],[8897809053,0,0,4,0,13,7684,1808,80,[73,57,125,5,82,38],[-1,-1,18],0],[8897816131,0,0,0,1,17,11108,1767,80,[66,53,47,44,-1,-1],[-1,-1,-1],0],[8897820445,0,0,132,0,16,8501,1952,80,[53,123,57,-1,-1,-1],[-1,-1,-1],0],[8897831712,0,0,0,1,23,13067,2890,80,[53,57,11,123,-1,-1],[-1,-1,-1],1],[8897833457,0,0,129,1,25,15973,3123,80,[47,66,28,63,53,107],[123,-1,-1],0],[8897842466,0,0,130,0,16,9928,2003,80,[48,5,38,57,125,42],[-1,-1,-1],0],[8897846470,0,0,0,0,18,8360,2417,80,[-1,-1,-1,57,123,53],[-1,-1,-1],1],[8897849657,0,0,130,1,17,9932,2026,80,[66,48,63,31,-1,5],[-1,-1,-1],0],[8897849797,0,0,132,1,21,20689,2100,80,[111,76,86,11,128,118],[-1,-1,-1],0],[8897851034,0,0,1,1,25,16820,2797,75,[34,57,124,76,26,5],[-1,-1,-1],1],[8897859553,0,0,128,1,18,12176,2053,80,[53,57,1,-1,12,-1],[-1,-1,-1],1],[8897860381,0,0,131,0,20,10610,2333,80,[126,5,2,1,66,48],[107,-1,123],0],[8897866635,0,0,1,1,14,7878,1573,80,[125,57,48,126,5,-1],[107,-1,-1],1],[8897872715,0,0,3,1,16,9175,1821,75,[-1,107,5,48,44,65],[-1,-1,-1],1],[8897874671,0,0,0,0,29,20489,3701,80,[5,76,48,2,-1,63],[101,-1,123],0],[8897875706,0,0,3,1,22,12779,2330,75,[57,48,5,124,118,-1],[-1,-1,-1],1],[8897876621,0,0,0,1,23,16780,3086,80,[53,48,44,7,46,-1],[-1,-1,-1],0],[8897882591,0,0,4,1,16,8216,1884,80,[48,53,-1,-1,125,31],[-1,-1,-1],1],[8897889005,0,0,130,0,22,15748,3424,80,[57,53,125,78,1,2],[107,-1,-1],0],[8897889703,0,0,130,1,24,16452,2896,75,[44,53,57,63,125,79],[107,-1,-1],1],[8897895356,0,0,1,1,18,9836,2051,80,[5,69,28,66,-1,17],[-1,-1,107],0],[8897895680,0,0,2,0,14,7680,1687,80,[107,123,-1,-1,53,57],[-1,-1,-1],0],[8897898137,0,0,132,1,22,15078,2549,80,[31,44,48,57,118,5],[107,-1,-1],0],[8897902806,0,0,128,1,18,10810,2073,80,[48,31,5,-1,57,69],[-1,-1,-1],0],[8897903610,0,0,128,1,15,13393,1355,80,[28,14,118,73,0,30],[-1,-1,-1],1],[8897904676,0,0,0,0,25,13586,3075,80,[53,57,50,123,1,-1],[-1,23,-1],0],[8897910482,0,0,2,0,17,12093,2419,80,[57,48,53,124,-1,-1],[23,-1,-1],1],[8897911874,0,0,4,1,16,9972,1763,80,[1,5,66,123,-1,2],[-1,-1,-1],0],[8897914689,0,0,130,1,21,14009,2249,80,[5,66,-1,28,48,110],[-1,-1,-1],0],[8897921600,0,0,3,1,16,8480,1789,80,[66,53,-1,31,123,-1],[-1,-1,-1],0],[8897930182,0,0,2,1,17,10536,1848,80,[84,38,-1,53,-1,57],[-1,114,-1],1],[8897936424,0,0,2,1,22,16180,2999,80,[31,48,57,5,11,118],[-1,-1,-1],1],[8897947107,0,0,2,1,15,8872,1659,80,[5,-1,125,-1,57,31],[-1,-1,-1],0],[8897955714,0,0,1,1,19,12907,2274,80,[5,57,48,-1,31,1],[-1,-1,-1],0],[8897967724,0,0,128,1,28,18407,4060,80,[31,-1,104,63,17,5],[-1,107,52],1],[8897967795,0,0,0,0,23,21035,2728,80,[54,48,14,118,55,62],[-1,50,108],0],[8897968649,0,0,0,1,18,11612,2192,80,[5,57,63,-1,-1,87],[107,-1,-1],1],[8897970501,0,0,129,0,12,5445,1889,75,[5,66,34,31,125,27],[38,-1,-1],1],[8897972101,0,0,3,0,20,9010,3001,80,[53,44,31,47,123,-1],[-1,-1,-1],0],[8897974541,0,0,128,0,21,11183,2727,80,[66,127,14,124,48,-1],[107,38,-1],0],[8897975026,0,0,130,0,14,7049,1944,80,[5,123,12,126,2,66],[112,92,-1],1],[8897981347,0,0,129,1,18,12933,1999,74,[66,46,8,53,47,-1],[-1,-1,-1],1],[8897985127,0,0,3,1,17,10630,2182,75,[53,-1,31,57,-1,-1],[-1,-1,-1],1],[8897987725,0,0,132,1,17,9477,1778,80,[57,-1,53,-1,-1,-1],[-1,-1,-1],0],[8897988489,0,0,129,1,20,13283,2652,80,[53,63,57,-1,-1,126],[-1,-1,-1],0],[8897990506,0,0,132,0,20,10504,2523,80,[57,14,125,-1,10,76],[-1,-1,-1],1],[8897997357,0,0,3,0,20,11405,2382,80,[53,123,48,57,-1,126],[107,-1,-1],0],[8898001973,0,0,0,0,18,10651,2273,80,[53,57,123,-1,38,11],[-1,-1,-1],0],[8898003594,0,0,130,0,19,11194,2329,80,[125,48,11,66,31,5],[-1,107,82],1],[8898009138,0,0,0,0,17,7595,2009,80,[125,44,38,48,66,5],[107,23,27],0],[8898015065,0,0,130,1,19,10326,2365,75,[25,34,5,125,66,116],[126,-1,-1],1],[8898018129,0,0,1,0,23,13617,3264,80,[101,31,127,47,2,5],[-1,124,-1],1],[8898018948,0,0,128,1,17,11598,2267,80,[66,31,48,83,-1,5],[-1,-1,-1],0],[8898027585,0,0,130,0,24,16997,2893,80,[11,48,127,57,5,-1],[-1,-1,-1],0],[8898033535,0,0,2,1,19,13217,2032,80,[53,-1,-1,1,2,107],[-1,-1,-1],0],[8898034123,0,0,3,1,18,10965,1928,74,[53,2,31,125,65,48],[-1,-1,-1],1],[8898036257,0,0,2,1,20,13109,2132,80,[-1,48,108,57,5,33],[107,-1,-1],0],[8898039766,0,0,3,0,13,6295,1730,80,[40,34,48,65,124,5],[18,-1,-1],1],[8898044082,0,0,130,1,16,9666,1974,80,[57,48,47,5,125,-1],[-1,-1,-1],0],[8898048328,0,0,2,0,20,11410,2725,80,[-1,-1,57,53,31,118],[-1,-1,-1],1],[8898063750,0,0,4,1,13,7911,1425,80,[53,57,-1,123,-1,-1],[107,-1,-1],0],[8898065347,0,0,0,1,23,15558,2643,80,[101,57,31,53,48,2],[107,124,-1],0],[8898066795,0,0,1,0,28,18533,3437,80,[58,48,57,123,5,76],[114,-1,38],0],[8898070419,0,0,2,1,21,13216,2472,80,[53,57,101,33,85,10],[-1,-1,-1],0],[8898075344,0,0,130,0,19,10784,2614,80,[53,11,-1,-1,57,-1],[-1,-1,-1],0],[8898079157,0,0,131,1,16,8792,1593,73,[123,57,53,-1,-1,-1],[-1,-1,-1],1],[8898079768,0,0,1,0,21,12030,2788,80,[53,48,2,-1,47,123],[-1,-1,-1],0],[8898082999,0,0,4,1,15,7871,1749,80,[53,-1,57,31,-1,-1],[-1,-1,-1],0],[8898089103,0,0,128,1,17,8163,1754,80,[5,12,66,48,69,-1],[107,-1,-1],0],[8898090118,0,0,0,0,21,11990,2668,80,[126,31,48,2,57,5],[107,38,123],1],[8898090644,0,0,3,0,25,14935,3798,75,[53,57,107,47,83,120],[-1,-1,-1],1],[8898093027,0,0,3,0,16,8099,2367,72,[53,27,2,66,-1,-1],[-1,-1,-1],1],[8898100079,0,0,1,1,20,15338,2525,80,[46,76,5,11,69,57],[107,-1,124],0],[8898100318,0,0,132,1,20,11940,2205,74,[-1,57,69,108,5,-1],[-1,-1,-1],1],[8898104578,0,0,130,1,25,13162,3124,74,[108,57,14,48,11,124],[107,-1,97],1],[8898105301,0,0,130,0,18,9673,2337,80,[108,53,47,66,18,-1],[-1,-1,-1],0],[8898106236,0,0,1,0,23,18530,3303,80,[63,44,46,57,47,53],[124,-1,107],0],[8898107193,0,0,130,1,14,12926,1170,80,[73,118,86,28,66,78],[-1,-1,-1],1],[8898107528,0,0,3,0,15,6722,2273,80,[11,66,31,5,120,33],[-1,123,-1],0],[8898109093,0,0,1,1,16,10884,1700,74,[79,57,53,-1,-1,-1],[-1,-1,-1],1],[8898111393,0,0,3,1,16,10777,2049,80,[57,5,-1,2,31,125],[-1,-1,-1],1],[8898126277,0,0,3,1,25,15127,2978,80,[53,48,57,124,31,-1],[-1,-1,-1],0],[8898128321,0,0,132,0,16,9513,2397,80,[5,38,11,31,57,47],[107,-1,-1],1],[8898130508,0,0,128,1,16,10140,2031,80,[2,48,5,66,69,31],[107,125,-1],1],[8898131084,0,0,131,1,19,13086,2176,75,[11,48,126,66,17,53],[-1,107,-1],1],[8898132749,0,0,2,1,23,13487,2911,80,[123,63,48,66,5,112],[87,107,77],1],[8898135836,0,0,128,1,22,12155,3147,80,[11,69,57,5,123,1],[-1,-1,-1],0],[8898136415,0,0,130,0,17,6659,2184,80,[14,48,44,123,66,79],[-1,-1,107],0],[8898143690,0,0,0,1,18,10201,1790,80,[123,11,57,31,53,107],[-1,-1,-1],0],[8898144588,0,0,1,0,19,15934,2945,80,[53,57,48,104,123,-1],[-1,-1,-1],0],[8898146741,0,0,130,0,18,8067,2135,75,[53,125,-1,65,-1,-1],[-1,-1,-1],1],[8898147394,0,0,3,0,21,13728,3004,80,[5,-1,2,28,63,48],[-1,-1,-1],0],[8898150381,0,0,129,1,21,13185,2540,80,[63,57,53,31,-1,-1],[107,-1,-1],0],[8898155545,0,0,129,0,13,5783,1713,80,[87,57,12,-1,5,31],[41,-1,-1],1],[8898156045,0,0,3,1,23,15494,2584,80,[53,48,31,87,57,63],[-1,-1,107],0],[8898157330,0,0,132,1,19,13203,2170,80,[53,111,66,126,38,112],[-1,-1,-1],0],[8898157592,0,0,4,1,23,14473,2868,80,[53,57,11,-1,31,1],[107,-1,-1],0],[8898159405,0,0,129,0,24,10622,3231,80,[53,-1,31,57,77,126],[9,112,-1],0],[8898167188,0,0,0,0,17,8781,2318,80,[48,57,31,5,2,123],[32,-1,114],0],[8898167708,0,0,3,1,20,10850,2132,80,[53,124,-1,48,-1,57],[-1,-1,-1],1],[8898168076,0,0,129,1,19,10454,1964,80,[48,53,66,124,39,-1],[-1,107,-1],0],[8898168739,0,0,129,0,21,12200,2753,80,[57,48,28,5,9,112],[-1,-1,123],1],[8898168760,0,0,129,0,14,7432,1639,80,[57,31,-1,5,103,-1],[23,102,-1],1],[8898170137,0,0,129,1,13,6470,1438,80,[5,31,66,69,126,46],[23,107,125],0],[8898173475,0,0,132,1,25,14540,2525,80,[53,66,123,1,28,46],[-1,-1,-1],0],[8898173665,0,0,132,0,19,11545,2451,80,[11,48,31,5,44,47],[-1,56,-1],0],[8898174060,0,0,0,0,15,7346,1930,75,[5,31,-1,102,103,11],[-1,-1,-1],1],[8898174069,0,0,1,1,23,12754,2543,80,[57,11,-1,5,125,1],[-1,-1,-1],1],[8898179989,0,0,1,1,15,11160,1765,80,[48,5,65,2,112,18],[18,-1,-1],1],[8898180177,0,0,130,0,23,13180,3032,80,[111,48,53,66,31,124],[107,-1,-1],0],[8898181186,0,0,2,1,20,11277,2166,75,[5,47,31,44,57,79],[94,-1,-1],1],[8898185235,0,0,132,1,26,19388,3341,80,[53,11,47,76,31,124],[73,12,57],0],[8898185466,0,0,4,0,23,14398,2715,80,[125,33,57,48,53,108],[-1,-1,-1],1],[8898185555,0,0,0,1,29,21108,3835,80,[48,47,11,46,53,76],[-1,31,-1],1],[8898185857,0,0,131,0,13,6161,1907,80,[48,-1,66,5,126,31],[-1,-1,-1],0],[8898188421,0,0,3,0,29,33514,3765,80,[74,11,13,21,105,71],[-1,-1,-1],0],[8898189707,0,0,2,0,13,5726,1822,80,[31,123,87,57,14,32],[107,-1,-1],1],[8898191081,0,0,1,1,19,11841,2311,80,[84,57,31,53,125,-1],[-1,-1,-1],1],[8898201540,0,0,2,0,18,9030,2156,80,[5,63,57,-1,107,31],[-1,23,-1],0],[8898204967,0,0,131,0,11,5695,1737,80,[-1,125,-1,66,-1,53],[-1,-1,-1],0],[8898210984,0,0,0,0,14,7724,2077,80,[66,124,48,53,-1,-1],[-1,-1,-1],0],[8898212590,0,0,130,1,19,11946,2214,80,[57,53,43,11,125,50],[41,-1,-1],1],[8898213835,0,0,1,1,20,12742,2189,80,[5,31,-1,48,57,2],[107,-1,-1],1],[8898215397,0,0,129,1,12,4585,1319,80,[31,87,14,66,34,125],[107,-1,-1],1],[8898220803,0,0,4,0,30,33322,4164,80,[53,47,57,4,51,29],[-1,-1,-1],0],[8898224755,0,0,128,1,14,8536,1902,80,[11,5,79,66,2,-1],[-1,-1,-1],0],[8898227378,0,0,132,1,19,12279,2179,80,[57,-1,53,31,11,-1],[94,-1,-1],1],[8898232028,0,0,129,1,15,9800,1968,80,[5,57,1,48,32,-1],[107,-1,-1],0],[8898234788,0,0,2,1,22,14637,2672,80,[31,57,11,14,126,76],[123,-1,50],1],[8898236402,0,0,2,1,19,12293,2211,80,[57,53,-1,-1,12,18],[-1,-1,-1],0],[8898239969,0,0,131,1,11,7991,1499,80,[41,12,48,125,5,57],[-1,-1,-1],0],[8898241282,0,0,1,1,14,7684,1841,80,[108,31,5,22,65,18],[-1,-1,-1],0],[8898249374,0,0,132,1,27,20554,3137,80,[11,48,28,57,107,53],[-1,-1,-1],0],[8898252654,0,0,128,0,13,7244,1840,80,[5,57,12,69,123,-1],[-1,-1,-1],0],[8898254501,0,0,128,0,22,12228,2928,80,[12,48,31,57,53,-1],[-1,-1,-1],1],[8898255530,0,0,1,0,15,7202,1984,80,[61,5,48,31,17,-1],[107,-1,-1],1],[8898256598,0,0,3,1,17,12597,2189,80,[5,63,103,24,48,-1],[96,-1,-1],1],[8898261211,0,0,1,0,18,8969,2190,80,[124,-1,53,-1,-1,57],[-1,-1,-1],1],[8898264536,0,0,4,1,18,10553,1898,80,[31,2,57,5,69,48],[123,-1,-1],1],[8898267122,0,0,1,0,18,12325,2525,80,[5,11,48,44,122,123],[-1,-1,-1],1],[8898273624,0,0,131,1,17,8874,1835,80,[125,66,48,87,5,-1],[-1,-1,-1],0],[8898274300,0,0,129,0,18,8431,2358,80,[123,57,48,69,5,31],[-1,-1,-1],0],[8898278742,0,0,131,1,16,8609,1646,80,[66,-1,48,-1,5,126],[-1,-1,-1],0],[8898279731,0,0,0,0,23,17767,2354,75,[118,86,66,13,73,111],[36,-1,-1],1],[8898283228,0,0,130,1,27,21138,3886,80,[34,57,11,53,85,1],[31,123,-1],1],[8898290086,0,0,130,1,22,15986,2289,80,[53,44,-1,31,48,-1],[-1,-1,-1],0],[8898293064,0,0,4,1,15,7434,1645,75,[123,5,57,31,69,-1],[107,-1,-1],1],[8898296380,0,0,132,1,15,9311,1835,71,[2,70,5,66,23,125],[-1,-1,-1],1],[8898299682,0,0,131,0,20,10679,2674,80,[48,44,53,38,47,31],[-1,-1,-1],0],[8898300262,0,0,1,0,18,10285,2256,80,[47,5,57,126,120,48],[18,-1,-1],1],[8898301428,0,0,1,0,23,13344,3303,72,[5,57,117,82,44,28],[-1,101,-1],1],[8898301672,0,0,129,0,17,9748,2457,80,[47,-1,124,5,57,48],[-1,-1,-1],0],[8898303515,0,0,0,1,15,10799,1817,80,[108,48,57,5,-1,-1],[-1,-1,-1],0],[8898304724,0,0,1,1,19,10145,2130,80,[53,57,-1,-1,-1,87],[107,-1,-1],1],[8898307563,0,0,1,0,17,8681,2472,80,[53,66,38,31,44,123],[32,-1,-1],0],[8898314686,0,0,3,0,18,6763,2333,80,[57,69,-1,-1,87,5],[-1,-1,-1],1],[8898317683,0,0,130,0,16,7189,1940,80,[11,107,57,31,123,5],[-1,-1,-1],1],[8898318265,0,0,4,1,24,16740,2819,80,[48,1,-1,57,53,47],[-1,-1,-1],0],[8898321680,0,0,0,0,12,5614,1653,80,[5,-1,123,-1,79,57],[-1,-1,-1],0],[8898322019,0,0,129,1,17,9586,1730,75,[73,48,5,-1,1,65],[107,-1,-1],1],[8898323979,0,0,132,0,21,8485,2801,80,[123,48,57,84,5,126],[23,107,-1],0],[8898326288,0,0,2,1,22,13992,2505,80,[-1,57,48,53,1,31],[-1,-1,-1],0],[8898327877,0,0,3,0,13,6384,1652,80,[31,66,53,124,107,-1],[-1,-1,-1],0],[8898332983,0,0,1,1,19,11305,1917,80,[38,-1,-1,44,53,57],[107,-1,-1],1],[8898333415,0,0,130,1,18,9447,1708,80,[57,53,-1,-1,-1,-1],[-1,-1,-1],1],[8898337607,0,0,130,1,26,15991,3280,80,[48,53,57,109,125,12],[114,95,-1],1],[8898337695,0,0,1,1,21,11412,2220,75,[126,52,44,53,-1,57],[-1,-1,-1],1],[8898344648,0,0,2,1,20,12091,2661,80,[31,57,53,44,-1,-1],[-1,-1,-1],1],[8898347946,0,0,0,1,22,21509,2195,80,[86,66,11,64,118,106],[-1,-1,-1],1],[8898348541,0,0,0,1,24,12320,2644,80,[5,34,11,31,125,2],[-1,-1,-1],0],[8898355748,0,0,3,1,19,8372,1815,80,[5,57,-1,79,69,12],[107,-1,-1],0],[8898355798,0,0,128,1,13,8151,1431,80,[66,63,5,-1,69,-1],[107,-1,-1],0],[8898360804,0,0,1,1,17,8569,2242,80,[53,123,-1,-1,57,-1],[-1,-1,-1],0],[8898362422,0,0,3,1,18,13663,2241,80,[53,57,123,31,1,50],[107,38,-1],0],[8898367940,0,0,128,1,21,13553,2314,80,[63,48,57,-1,5,69],[-1,-1,-1],0],[8898368655,0,0,4,1,17,11638,1830,80,[11,53,-1,50,57,124],[-1,-1,-1],1],[8898368816,0,0,2,1,18,11863,2171,80,[-1,44,53,57,31,-1],[114,-1,-1],0],[8898373875,0,0,3,1,20,13265,2269,80,[48,11,65,44,5,-1],[87,-1,-1],1],[8898378261,0,0,0,1,20,11604,2551,80,[53,57,101,-1,63,126],[107,-1,-1],0],[8898378524,0,0,3,1,18,11116,2097,80,[-1,57,87,53,2,-1],[-1,-1,-1],0],[8898380939,0,0,1,0,11,5609,1814,80,[5,11,66,123,-1,-1],[107,-1,-1],0],[8898384912,0,0,130,1,16,10300,1961,80,[53,57,11,125,-1,23],[-1,-1,-1],0],[8898386569,0,0,2,0,23,9281,3357,80,[87,44,48,31,-1,5],[107,-1,-1],0],[8898387293,0,0,0,1,19,13175,2156,80,[57,31,48,125,122,53],[33,-1,-1],0],[8898388131,0,0,0,0,17,5941,1965,80,[18,107,57,31,5,125],[-1,-1,-1],1],[8898388548,0,0,4,0,15,7692,1961,80,[5,48,123,65,-1,69],[-1,-1,-1],1],[8898391193,0,0,2,1,21,12371,2567,75,[5,44,111,31,124,2],[107,66,-1],1],[8898396009,0,0,128,0,19,11337,2453,80,[57,85,53,48,112,31],[107,-1,-1],1],[8898397132,0,0,130,1,21,10894,1991,80,[61,53,87,57,-1,31],[-1,-1,-1],1],[8898398157,0,0,128,0,22,14637,3257,80,[53,11,118,-1,123,66],[33,122,107],0],[8898398990,0,0,129,0,24,17794,3103,80,[2,110,123,5,48,63],[55,107,-1],0],[8898402619,0,0,1,0,14,5279,1810,80,[28,5,-1,31,38,-1],[107,-1,-1],1],[8898403367,0,0,0,1,19,10511,2406,80,[5,-1,119,47,57,38],[107,-1,31],0],[8898404096,0,0,129,1,14,8313,1625,80,[57,12,125,5,69,-1],[107,-1,-1],1],[8898405791,0,0,3,0,12,4776,1710,80,[57,124,-1,-1,-1,5],[-1,-1,-1],0],[8898413337,0,0,130,1,24,14771,2634,80,[11,83,48,66,53,-1],[-1,-1,-1],0],[8898415342,0,0,3,1,15,10679,1754,80,[69,48,66,126,5,-1],[-1,-1,-1],0],[8898419651,0,0,132,1,17,12417,1842,73,[57,3,38,85,48,5],[107,-1,-1],1],[8898425131,0,0,132,0,14,7644,1915,80,[57,69,11,14,12,-1],[107,-1,-1],0],[8898435332,0,0,2,1,19,9992,2028,80,[57,-1,53,125,23,-1],[107,-1,-1],1],[8898440131,0,0,1,0,19,13317,2394,80,[118,14,11,58,16,66],[-1,-1,-1],0],[8898440185,0,0,3,0,25,10837,3878,75,[65,-1,63,-1,2,14],[72,18,22],1],[8898441337,0,0,4,1,19,10390,1931,80,[48,123,57,14,108,-1],[38,-1,-1],0],[8898451527,0,0,130,1,16,9109,2200,80,[48,57,5,-1,69,12],[31,107,-1],1],[8898453678,0,0,2,1,15,10660,2029,80,[31,47,57,5,2,123],[50,-1,-1],1],[8898456012,0,0,4,1,17,11686,1751,80,[65,2,-1,44,5,28],[107,87,-1],1],[8898456763,0,0,1,1,18,11892,2200,75,[57,-1,48,10,107,53],[12,50,38],1],[8898459291,0,0,129,1,16,9957,1945,80,[17,48,53,66,-1,-1],[-1,-1,-1],1],[8898461859,0,0,3,1,26,14879,2867,80,[31,44,2,53,28,17],[-1,66,-1],0],[8898461892,0,0,3,1,17,11356,1898,80,[57,53,-1,48,-1,-1],[-1,-1,-1],0],[8898466924,0,0,3,1,18,11079,2009,80,[57,53,11,124,-1,107],[-1,-1,-1],0],[8898470835,0,0,1,1,24,12516,3255,80,[31,48,14,53,44,-1],[101,-1,21],0],[8898475485,0,0,128,0,18,9847,2172,80,[53,48,44,65,31,123],[-1,-1,-1],1],[8898482236,0,0,128,0,12,6490,1855,80,[87,48,124,5,57,126],[107,-1,23],0],[8898483508,0,0,4,1,16,11203,1768,80,[57,5,44,48,-1,31],[107,-1,-1],0],[8898484911,0,0,0,0,22,9893,2786,80,[123,1,101,66,2,5],[107,-1,-1],0],[8898487607,0,0,130,1,25,17695,3163,80,[11,57,31,118,53,116],[-1,23,124],0],[8898489758,0,0,129,0,20,13395,3072,80,[2,47,48,5,-1,44],[-1,-1,-1],1],[8898492380,0,0,129,0,26,16017,3401,80,[31,2,110,5,63,48],[-1,52,107],0],[8898496802,0,0,128,1,25,16799,2923,80,[57,53,48,2,85,77],[112,-1,-1],1],[8898498284,0,0,4,0,27,13206,3911,80,[11,53,47,31,123,57],[-1,-1,-1],0],[8898503966,0,0,132,0,21,8560,2621,80,[5,57,48,107,31,-1],[-1,-1,-1],0],[8898514617,0,0,131,0,13,9290,2137,80,[5,66,44,55,123,126],[33,107,90],0],[8898515627,0,0,4,1,18,10682,2446,74,[28,57,50,56,5,48],[20,-1,-1],1],[8898516150,0,0,4,1,21,10524,2804,80,[123,53,57,-1,11,31],[-1,-1,-1],0],[8898521332,0,0,130,0,13,7622,2392,80,[31,28,48,125,5,-1],[107,-1,-1],0],[8898521673,0,0,1,1,16,8302,1729,80,[14,100,57,123,-1,126],[-1,-1,-1],0],[8898522281,0,0,0,1,24,15716,2512,80,[53,57,-1,17,118,126],[-1,-1,-1],0],[8898530109,0,0,0,1,22,14108,2386,75,[28,48,57,5,63,125],[107,23,-1],1],[8898530329,0,0,0,0,17,9588,2297,80,[123,-1,-1,57,53,11],[107,-1,-1],1],[8898532595,0,0,1,0,26,16711,2972,80,[47,48,11,118,31,53],[124,-1,-1],0],[8898533615,0,0,128,1,26,17503,2900,80,[48,53,31,66,-1,11],[95,1,-1],0],[8898535262,0,0,4,1,21,14368,2772,80,[50,11,48,76,2,5],[-1,-1,-1],1],[8898538164,0,0,1,1,26,12440,3088,80,[119,48,11,-1,53,123],[-1,-1,-1],0],[8898539175,0,0,131,0,16,7171,2265,80,[11,66,2,5,-1,126],[-1,-1,-1],1],[8898548319,0,0,128,0,14,7820,1829,80,[53,57,123,-1,-1,-1],[-1,-1,-1],1],[8898549508,0,0,131,0,15,6844,2271,74,[66,-1,53,103,31,102],[-1,-1,-1],1],[8898550252,0,0,0,1,24,17012,3136,80,[11,48,2,57,53,123],[-1,-1,-1],0],[8898550277,0,0,2,1,27,18819,3806,80,[66,48,11,53,85,2],[-1,-1,-1],0],[8898550609,0,0,129,1,27,22080,3762,80,[53,57,2,63,76,46],[103,31,123],0],[8898551335,0,0,2,1,17,12189,2041,80,[66,-1,48,5,-1,2],[-1,-1,-1],0],[8898555407,0,0,4,1,16,12214,2213,80,[53,70,66,2,17,126],[107,123,-1],1],[8898560151,0,0,3,1,15,9759,1579,80,[5,77,-1,85,57,31],[-1,-1,-1],1],[8898561609,0,0,1,1,18,14337,2545,80,[79,48,123,53,46,57],[-1,31,-1],1],[8898562909,0,0,131,1,20,10275,2056,80,[108,47,31,123,-1,53],[107,23,-1],0],[8898563857,0,0,130,1,21,13232,2428,80,[57,31,11,53,47,123],[-1,-1,107],1],[8898566818,1,0,128,1,13,6989,1385,80,[5,111,12,-1,107,79],[-1,-1,-1],1],[8898567129,1,0,4,0,13,5254,1969,80,[57,31,56,5,-1,126],[-1,-1,-1],1],[8898569325,1,0,130,0,17,9462,2309,80,[53,57,12,123,107,103],[-1,-1,-1],0],[8898576730,1,0,129,1,26,18110,2802,80,[53,48,57,2,1,-1],[-1,-1,-1],1],[8898578914,1,0,4,0,13,7684,1855,80,[5,57,2,124,17,31],[-1,-1,-1],1],[8898579676,1,0,1,1,21,9889,2320,80,[5,57,48,125,107,12],[31,-1,-1],1],[8898580671,1,0,4,1,24,14110,2781,73,[5,34,57,63,11,-1],[-1,-1,-1],1],[8898581035,1,0,128,0,16,8114,2023,80,[125,81,57,5,34,126],[20,-1,-1],0],[8898583964,1,0,3,1,16,9414,1799,73,[57,63,31,43,5,-1],[-1,-1,-1],1],[8898586181,1,0,3,1,17,9766,1999,80,[65,124,48,5,70,11],[107,-1,-1],0],[8898586737,1,0,129,0,19,10137,2554,80,[-1,53,57,125,48,-1],[-1,-1,-1],0],[8898586961,1,0,4,1,20,14312,2426,80,[47,28,48,125,-1,5],[31,-1,-1],0],[8898596235,1,0,4,1,27,20090,3668,80,[53,11,57,46,1,48],[123,31,-1],0],[8898604196,1,0,129,1,18,11966,2224,80,[108,123,57,103,53,49],[38,-1,107],0],[8898606743,1,0,0,0,15,5314,2199,80,[56,20,5,-1,57,123],[-1,-1,-1],1],[8898609663,1,0,132,1,16,9873,2064,80,[57,53,-1,123,18,31],[107,18,-1],1],[8898612384,1,0,1,0,23,11475,2826,80,[48,44,47,53,31,66],[124,-1,-1],0],[8898615029,1,0,132,1,20,11517,2403,80,[11,48,53,66,-1,31],[107,-1,-1],0],[8898615809,1,0,129,0,13,6967,1939,80,[-1,53,57,123,-1,12],[-1,-1,-1],0],[8898619053,1,0,128,0,15,6430,2177,80,[44,47,31,14,125,66],[107,32,97],0],[8898623276,1,0,132,0,16,10771,2320,75,[108,53,125,73,-1,66],[-1,-1,-1],1],[8898627228,1,0,1,0,26,16994,4116,80,[11,57,63,5,48,47],[-1,107,-1],0],[8898644727,1,0,2,1,16,9651,1868,80,[69,57,48,-1,5,107],[-1,-1,-1],0],[8898654097,1,0,2,1,16,8917,1941,73,[57,69,-1,124,5,-1],[107,-1,-1],1],[8898654980,1,0,3,0,14,4415,2122,80,[102,66,31,27,123,5],[-1,-1,-1],0],[8898655280,1,0,129,1,26,18474,2855,80,[5,55,57,48,11,63],[124,-1,-1],0],[8898662724,1,0,128,0,17,10255,2348,80,[57,44,123,119,69,5],[-1,107,-1],0],[8898667439,1,0,4,1,24,14866,3284,80,[53,11,48,57,126,2],[101,107,123],0],[8898672868,1,0,128,0,14,10826,2317,80,[53,125,79,57,-1,-1],[107,-1,-1],0],[8898683794,1,0,128,0,10,3876,1576,80,[-1,-1,-1,5,-1,48],[-1,-1,-1],0],[8898690214,1,0,131,0,24,12276,3410,80,[48,5,123,63,57,31],[-1,-1,-1],1],[8898700940,1,0,2,0,22,12631,2720,73,[2,77,66,85,126,53],[112,-1,-1],1],[8898701609,1,0,130,1,13,8568,1615,80,[53,66,-1,48,-1,-1],[-1,-1,-1],0],[8898703674,1,0,0,0,15,7064,2426,73,[48,57,5,-1,-1,123],[-1,-1,-1],1],[8898704530,1,0,129,0,14,7335,1897,75,[66,69,36,82,5,31],[107,123,-1],1],[8898706378,1,0,130,1,16,10242,1755,74,[57,44,-1,126,5,1],[107,-1,-1],1],[8898713795,1,0,3,0,12,5065,1443,80,[87,48,12,17,123,5],[107,-1,-1],0],[8898715049,1,0,4,1,19,13347,2099,80,[5,108,57,48,36,11],[107,-1,-1],0],[8898721117,1,0,129,0,15,9016,1969,80,[98,-1,123,-1,53,57],[-1,-1,-1],0],[8898721705,1,0,2,0,17,7277,2520,80,[28,124,57,14,-1,-1],[-1,-1,-1],0],[8898721711,1,0,4,1,15,7353,2110,71,[123,5,82,31,-1,2],[87,-1,-1],1],[8898730105,1,0,1,0,15,8653,2087,80,[123,53,66,48,126,-1],[107,-1,-1],0],[8898732126,1,0,2,0,18,10215,2518,80,[5,69,57,11,123,-1],[107,-1,-1],0],[8898739292,1,0,128,0,13,6994,1488,80,[53,65,-1,123,-1,79],[107,-1,-1],0],[8898742114,1,0,1,1,20,14454,1983,80,[50,35,48,125,5,1],[-1,-1,65],0],[8898746278,1,0,128,0,16,9229,2191,72,[-1,53,125,57,-1,-1],[-1,-1,-1],1],[8898746520,1,0,1,1,15,8569,1801,74,[-1,23,-1,57,69,5],[-1,-1,-1],1],[8898751394,1,0,1,1,24,13168,2520,80,[44,66,127,5,-1,-1],[-1,-1,-1],0],[8898754636,1,0,2,1,23,14394,2632,80,[66,48,53,107,2,-1],[52,50,-1],0],[8898755243,1,0,0,0,12,6355,1761,80,[66,125,23,53,-1,126],[-1,107,-1],0],[8898756460,1,0,130,0,21,10965,3398,73,[57,63,124,9,-1,5],[107,-1,-1],1],[8898758114,1,0,130,0,24,12499,2952,80,[118,69,125,15,-1,31],[-1,-1,-1],0],[8898763065,1,0,0,1,13,7954,1472,80,[48,-1,65,5,12,125],[-1,-1,-1],0],[8898768323,1,0,132,1,16,12988,2082,80,[57,107,5,2,118,-1],[-1,-1,-1],1],[8898769042,1,0,2,1,27,15576,3701,75,[48,-1,121,1,2,14],[107,-1,-1],1],[8898770420,1,0,4,1,28,32563,3166,80,[86,118,113,29,51,59],[-1,-1,-1],0],[8898773868,1,0,130,0,16,12728,2781,80,[47,48,50,66,53,2],[38,-1,107],1],[8898775171,1,0,3,1,12,6913,1423,72,[-1,5,-1,57,-1,-1],[-1,-1,-1],1],[8898777657,1,0,2,0,17,8091,2155,80,[123,5,48,57,126,47],[107,-1,-1],0],[8898781991,1,0,0,1,16,10303,1693,80,[5,66,48,23,31,1],[-1,-1,-1],0],[8898787136,1,0,2,0,20,9975,2700,80,[123,28,15,31,5,66],[-1,107,-1],1],[8898788987,1,0,129,1,19,13079,2209,75,[5,48,63,57,124,56],[126,-1,-1],1],[8898800625,1,0,3,0,15,7193,2272,80,[66,48,34,12,-1,5],[-1,-1,-1],0],[8898800866,1,0,1,0,21,8923,2772,74,[5,57,31,123,2,126],[126,-1,-1],1],[8898801798,1,0,131,0,15,5792,1970,80,[5,66,69,126,-1,32],[-1,-1,-1],1],[8898802149,1,0,128,0,8,4206,1398,80,[124,22,66,69,5,-1],[-1,-1,-1],0],[8898804550,1,0,130,0,11,5241,1795,80,[-1,5,-1,57,-1,-1],[-1,-1,-1],0],[8898806307,1,0,0,1,20,11677,2692,80,[66,53,48,125,31,1],[-1,-1,-1],0],[8898809312,1,0,128,1,15,9433,1699,80,[53,-1,57,-1,-1,-1],[-1,-1,-1],0],[8898811802,1,0,0,1,26,15155,3360,80,[11,53,46,57,-1,123],[107,23,79],1],[8898814343,1,0,2,1,22,13345,2894,80,[53,66,52,1,47,2],[-1,-1,-1],1],[8898815670,1,0,0,1,25,18144,3024,80,[57,118,101,2,53,122],[-1,-1,-1],1],[8898816116,1,0,132,0,23,11155,3128,80,[47,11,48,57,5,31],[-1,-1,107],1],[8898817205,1,0,0,1,18,11574,2533,80,[53,101,57,124,2,126],[-1,-1,-1],0],[8898817715,1,0,4,0,13,7950,1696,80,[5,42,44,57,107,124],[38,41,-1],1],[8898817929,1,0,4,1,12,7807,1310,80,[5,57,103,-1,107,-1],[-1,-1,-1],0],[8898823409,1,0,2,1,17,10877,1864,80,[119,-1,57,48,53,123],[-1,-1,-1],1],[8898825233,1,0,132,0,14,5775,1787,75,[5,48,126,66,31,-1],[-1,-1,-1],1],[8898825769,1,0,0,0,22,11307,2498,80,[66,48,-1,5,2,117],[-1,-1,-1],1],[8898830657,1,0,0,1,20,14770,3062,80,[53,57,83,31,123,2],[-1,-1,-1],0],[8898835004,1,0,131,1,16,10627,1940,80,[5,123,57,48,126,-1],[38,107,-1],0],[8898836362,1,0,129,1,21,12067,2414,80,[57,44,31,-1,123,53],[-1,-1,-1],0],[8898840647,1,0,4,0,13,5757,1738,80,[53,-1,12,66,-1,-1],[39,-1,-1],0],[8898845388,1,0,0,1,19,10120,2535,80,[11,-1,2,66,5,48],[-1,-1,-1],1],[8898845459,1,0,4,1,16,8314,1692,80,[57,125,-1,126,5,69],[-1,-1,-1],0],[8898849322,1,0,3,1,16,9615,1584,75,[118,66,5,48,-1,-1],[-1,-1,-1],1],[8898851185,1,0,2,0,15,8449,1903,80,[53,126,-1,57,123,107],[-1,-1,-1],0],[8898857305,1,0,129,1,19,12716,2443,80,[48,1,69,5,123,2],[-1,-1,-1],0],[8898859227,1,0,3,0,16,11283,2360,80,[66,118,28,115,107,123],[27,-1,-1],1],[8898860216,1,0,132,1,23,13287,2995,80,[57,-1,1,53,-1,17],[-1,-1,-1],1],[8898862593,1,0,129,1,25,13643,3034,80,[11,2,47,57,53,-1],[-1,-1,-1],1],[8898875545,1,0,132,1,20,11166,2290,80,[57,53,125,10,11,31],[-1,-1,-1],1],[8898879926,1,0,3,0,12,6815,1793,75,[-1,57,53,-1,-1,-1],[-1,-1,-1],1],[8898881840,1,0,4,1,25,16125,3356,80,[100,66,28,48,12,53],[-1,-1,-1],0],[8898884369,1,0,3,0,20,12923,2619,80,[5,118,88,79,10,66],[-1,-1,-1],1],[8898886301,1,0,3,0,12,3708,1721,80,[66,-1,-1,-1,-1,5],[-1,-1,107],0],[8898900173,1,0,128,1,21,12516,2163,75,[14,11,111,44,66,125],[-1,-1,-1],1],[8898903012,1,0,129,1,20,13244,2610,80,[5,123,44,57,48,2],[125,-1,107],0],[8898907413,1,0,2,1,14,10177,1714,80,[42,53,32,123,57,-1],[90,-1,-1],1],[8898910201,1,0,2,1,11,6200,1313,80,[123,5,-1,23,48,66],[90,-1,-1],0],[8898912119,1,0,128,0,20,13077,2492,75,[57,11,53,123,-1,31],[-1,-1,-1],1],[8898921624,1,0,4,1,23,14325,2373,80,[53,57,48,-1,46,-1],[-1,-1,-1],0],[8898923366,1,0,1,0,9,3177,1563,75,[123,5,-1,31,107,-1],[-1,-1,-1],1],[8898927734,1,0,128,0,16,9306,2451,80,[53,48,-1,119,123,66],[-1,-1,-1],0],[8898929233,1,0,130,1,22,15334,2745,80,[125,53,44,46,2,1],[79,-1,-1],1],[8898942180,1,0,128,0,12,5115,1830,74,[66,27,5,123,48,31],[107,-1,-1],1],[8898949917,1,0,130,1,24,12730,2493,80,[47,57,2,5,48,31],[125,-1,-1],1],[8898951558,1,0,4,1,21,11589,2553,80,[53,57,31,125,103,-1],[107,-1,-1],0],[8898956014,1,0,1,1,13,8544,1619,75,[125,57,53,107,40,-1],[-1,-1,-1],1],[8898961078,1,0,1,0,17,9773,2304,80,[11,14,57,2,107,125],[-1,-1,-1],0],[8898967008,1,0,130,1,17,11912,1772,80,[53,57,107,-1,-1,-1],[-1,-1,-1],0],[8898968545,1,0,130,1,18,9534,2212,75,[53,-1,57,-1,-1,126],[107,-1,-1],1],[8898970176,1,0,0,0,24,13500,3439,80,[5,44,2,123,66,108],[114,107,-1],0],[8898976899,1,0,128,0,26,15236,3059,80,[53,28,123,2,57,47],[-1,-1,-1],0],[8898977730,1,0,4,1,16,8526,1711,80,[-1,57,31,11,108,14],[-1,-1,-1],0],[8898984484,1,0,130,1,21,12676,2304,80,[57,53,31,19,-1,112],[-1,-1,-1],0],[8898987450,1,0,0,0,19,10547,2212,80,[5,48,82,2,123,66],[94,33,-1],1],[8898997780,1,0,2,0,14,6877,2132,80,[5,57,48,56,125,-1],[107,-1,-1],0],[8898998321,1,0,4,1,20,15252,2133,80,[10,57,44,-1,2,53],[-1,-1,-1],0],[8898999830,1,0,1,1,24,17990,2660,74,[53,48,104,11,-1,65],[-1,-1,107],1],[8899007011,1,0,0,0,18,8632,2369,80,[14,-1,11,57,48,107],[-1,-1,-1],1],[8899019505,1,0,1,0,18,10388,2056,80,[48,66,11,-1,53,-1],[-1,-1,-1],0],[8899020762,1,0,0,0,15,6722,2085,80,[122,-1,57,90,126,5],[-1,-1,-1],0],[8899022968,1,0,129,1,20,12521,2088,80,[48,47,57,5,-1,124],[-1,-1,107],0],[8899025878,1,0,132,0,16,11493,2189,80,[57,5,69,42,78,28],[-1,-1,-1],1],[8899030260,1,0,4,1,18,12960,2169,80,[57,-1,53,38,-1,63],[-1,-1,-1],1],[8899031136,1,0,1,1,17,10353,1898,80,[31,48,108,-1,66,53],[-1,-1,-1],0],[8899037054,1,0,132,0,10,4199,1525,80,[5,66,126,61,125,27],[12,107,-1],0],[8899037642,1,0,131,0,18,9217,2790,80,[5,66,48,2,31,11],[-1,-1,125],0],[8899038522,1,0,131,1,26,19249,3317,80,[57,34,118,53,48,47],[-1,-1,-1],0],[8899039806,1,0,1,0,16,5778,2433,80,[-1,5,48,79,112,40],[65,-1,-1],0],[8899044406,1,0,129,1,19,11349,2572,80,[123,66,79,111,31,53],[-1,-1,-1],0],[8899051909,1,0,2,0,15,8086,1742,74,[122,5,10,33,48,57],[-1,-1,-1],1],[8899054450,1,0,0,0,14,7330,2253,80,[57,123,69,5,-1,20],[-1,-1,107],0],[8899059183,1,0,2,0,17,8490,2375,80,[48,5,47,66,31,123],[-1,-1,-1],0],[8899062742,1,0,1,0,21,12699,2629,80,[48,66,124,53,47,1],[107,-1,-1],0],[8899064668,1,0,2,0,18,9163,2288,80,[57,123,-1,53,-1,-1],[-1,-1,-1],0],[8899066356,1,0,132,0,15,6290,2199,80,[123,2,31,47,107,14],[66,-1,-1],0],[8899067438,1,0,0,0,18,9274,2319,80,[48,-1,57,5,69,124],[-1,-1,-1],0],[8899068139,1,0,129,1,22,15983,2477,75,[2,53,34,57,11,38],[-1,-1,-1],1],[8899069931,1,0,132,0,21,18727,2014,80,[86,60,29,11,118,62],[91,19,-1],1],[8899070219,1,0,131,0,19,11406,2807,80,[53,66,123,-1,79,118],[107,-1,-1],0],[8899079584,1,0,0,0,9,4135,1491,80,[-1,57,123,-1,14,-1],[107,-1,-1],0],[8899086371,1,0,129,0,20,8666,2700,80,[63,44,-1,5,123,126],[-1,-1,-1],0],[8899087733,1,0,4,0,12,6657,1908,80,[5,100,69,123,-1,66],[-1,-1,-1],0],[8899089217,1,0,130,0,14,6861,2160,80,[31,108,48,123,-1,14],[-1,-1,-1],1],[8899090315,1,0,3,0,11,7347,1437,80,[129,66,86,118,38,129],[-1,-1,-1],0],[8899091897,1,0,130,0,18,8817,2506,80,[31,123,57,52,53,-1],[-1,-1,-1],0],[8899096492,1,0,130,1,19,11919,2262,80,[78,125,53,57,11,-1],[107,-1,-1],0],[8899096735,1,0,128,1,19,13263,2057,80,[111,123,53,39,38,66],[-1,107,-1],0],[8899097454,1,0,2,1,20,17121,2049,74,[10,118,53,-1,55,57],[90,-1,-1],1],[8899104528,1,0,129,0,19,9412,2737,80,[57,111,11,5,125,-1],[-1,-1,-1],1],[8899105125,1,0,2,1,25,12850,3264,80,[46,-1,57,48,11,5],[-1,-1,-1],0],[8899106363,1,0,131,1,25,15820,3043,80,[53,57,11,123,31,46],[-1,-1,-1],0],[8899110247,1,0,130,1,24,14725,2616,80,[107,123,11,1,57,53],[-1,-1,-1],0],[8899110292,1,0,0,0,10,3103,1318,80,[5,66,31,-1,-1,-1],[-1,-1,-1],0],[8899112810,1,0,132,0,17,11142,2208,80,[12,57,2,125,53,126],[107,-1,-1],0],[8899116706,1,0,129,0,21,14002,2616,80,[108,53,48,125,120,73],[89,-1,-1],0],[8899116955,1,0,2,0,16,10051,1987,80,[53,57,48,123,-1,-1],[-1,-1,-1],0],[8899117798,1,0,129,0,15,7347,2338,80,[107,31,57,125,5,-1],[-1,-1,-1],0],[8899129600,1,0,2,0,16,5108,1634,80,[17,-1,87,5,66,-1],[-1,-1,-1],1],[8899131355,1,0,4,0,10,4193,1435,80,[69,65,5,123,-1,18],[31,-1,-1],0],[8899133341,1,0,0,1,17,9553,1982,73,[57,11,-1,28,5,-1],[-1,-1,-1],1],[8899135849,1,0,3,1,21,12845,2383,75,[125,11,57,2,48,5],[-1,-1,-1],1],[8899135850,1,0,4,0,20,10707,2692,80,[123,57,53,2,32,85],[-1,-1,-1],0],[8899138727,1,0,3,1,20,12342,2400,80,[65,32,48,53,2,125],[-1,-1,-1],0],[8899146187,1,0,3,0,12,6417,1571,80,[-1,5,2,66,31,45],[-1,-1,-1],0],[8899147026,1,0,132,1,16,8365,1939,80,[53,-1,31,103,-1,47],[-1,-1,107],0],[8899149426,1,0,129,1,20,12755,2380,80,[5,66,48,28,-1,2],[-1,-1,-1],0],[8899155760,1,0,128,1,19,12083,1967,80,[57,31,53,108,125,126],[-1,107,-1],0],[8899156384,1,0,129,0,11,5601,1450,75,[14,66,97,-1,55,-1],[-1,-1,-1],1],[8899161562,1,0,1,1,23,15409,2660,80,[11,-1,57,-1,53,48],[-1,-1,-1],0],[8899162166,1,0,3,1,23,14009,2721,80,[2,46,53,44,31,65],[107,-1,-1],1],[8899169564,1,0,131,1,16,10170,1851,80,[-1,125,53,-1,18,57],[-1,-1,-1],0],[8899179703,1,0,129,0,15,8334,1974,80,[100,124,66,53,40,-1],[-1,-1,-1],0],[8899188591,1,0,128,0,16,8067,2275,75,[14,44,119,11,-1,66],[-1,-1,-1],1],[8899196533,1,0,0,1,21,13039,2579,80,[48,57,44,53,-1,-1],[-1,-1,-1],1],[8899198842,1,0,129,0,19,13852,2275,74,[80,118,86,66,11,10],[75,-1,-1],1],[8899202121,1,0,3,0,18,11566,1875,80,[118,16,66,29,-1,86],[-1,-1,-1],1],[8899206403,1,0,0,1,26,17198,2994,80,[31,44,57,48,11,53],[-1,101,-1],0],[8899207135,1,0,131,0,17,8308,2239,80,[53,57,123,-1,-1,-1],[107,-1,-1],0],[8899211582,1,0,0,1,19,9132,2114,80,[44,48,57,-1,126,5],[107,-1,-1],0],[8899212760,1,0,128,0,17,9086,2082,80,[53,57,123,114,12,107],[-1,-1,-1],0],[8899215647,1,0,1,0,20,10298,2601,80,[123,53,31,57,126,-1],[-1,-1,-1],0],[8899219722,1,0,3,0,15,6810,2116,80,[69,57,5,124,-1,-1],[107,-1,-1],0],[8899220684,1,0,4,1,14,8812,1450,80,[108,-1,83,73,-1,5],[-1,107,-1],0],[8899223879,1,0,129,1,16,9846,1892,80,[5,66,48,2,123,28],[-1,-1,-1],0],[8899233956,1,0,131,0,21,12016,2878,80,[-1,11,48,5,47,57],[87,107,125],0],[8899240216,1,0,2,1,13,7840,1408,80,[53,48,31,40,18,65],[123,-1,-1],0],[8899243710,1,0,129,1,22,12767,2921,74,[46,48,57,53,47,31],[-1,-1,-1],1],[8899246698,1,0,130,0,12,5661,2090,80,[84,5,66,31,-1,123],[-1,-1,-1],0],[8899247458,1,0,4,0,16,6413,2042,80,[107,5,125,126,126,82],[94,-1,-1],0],[8899253081,1,0,129,0,13,7841,1847,80,[2,-1,66,123,-1,53],[-1,-1,-1],0],[8899254470,1,0,4,1,20,12165,1909,80,[2,47,66,5,44,-1],[-1,-1,-1],1],[8899258105,1,0,131,0,15,6024,2028,80,[57,31,56,5,125,20],[12,-1,-1],0],[8899259445,1,0,130,0,23,10571,3573,80,[66,53,101,-1,26,123],[-1,-1,-1],0],[8899269760,1,0,3,0,13,6924,2123,80,[5,33,65,123,48,82],[-1,-1,-1],0],[8899272073,1,0,4,0,17,8611,2365,80,[53,125,57,-1,31,126],[-1,-1,-1],0],[8899273321,1,0,0,1,15,11367,1685,80,[53,57,46,-1,-1,-1],[-1,-1,-1],0],[8899273484,1,0,132,1,16,10079,1886,80,[57,69,44,87,-1,5],[-1,-1,-1],0],[8899278782,1,0,3,0,21,10445,2404,80,[44,57,5,126,22,85],[-1,-1,-1],0],[8899280819,1,0,132,1,24,15517,2796,80,[124,53,44,66,76,2],[107,-1,-1],1],[8899292644,1,0,131,1,26,11315,3045,80,[5,116,44,11,125,47],[31,101,50],1],[8899296580,1,0,132,1,17,9046,1874,80,[57,69,11,31,5,-1],[107,-1,-1],0],[8899301594,1,0,130,1,17,9654,1920,80,[5,57,69,108,123,-1],[107,-1,-1],0],[8899303713,1,0,130,0,13,7273,1769,80,[5,48,57,123,107,-1],[-1,-1,-1],0],[8899307987,1,0,3,1,30,22312,4433,80,[44,125,47,53,11,104],[116,107,31],0],[8899308259,1,0,132,1,20,13671,2724,80,[48,63,44,5,2,66],[-1,-1,123],0],[8899309078,1,0,128,0,25,19876,3129,80,[53,57,48,123,76,118],[101,32,-1],0],[8899315207,1,0,129,0,20,14651,2211,75,[31,5,66,11,118,76],[-1,-1,-1],1],[8899318847,1,0,132,1,22,12105,3045,80,[65,28,53,-1,2,-1],[95,-1,-1],0],[8899321439,1,0,4,1,18,10523,1835,74,[53,57,123,-1,-1,107],[-1,-1,-1],1],[8899321833,1,0,1,1,21,12710,2299,80,[11,57,-1,5,69,31],[-1,-1,-1],0],[8899324274,1,0,129,1,17,9516,2122,80,[103,107,123,53,-1,57],[18,-1,-1],0],[8899324739,1,0,132,0,17,9519,2312,80,[57,125,48,31,5,126],[-1,-1,107],1],[8899325928,1,0,129,1,16,9453,1720,80,[56,48,5,66,28,124],[-1,-1,-1],0],[8899340331,1,0,2,0,19,9672,2402,80,[47,-1,57,5,2,123],[-1,-1,-1],0],[8899340420,1,0,128,1,17,10700,1938,80,[-1,57,53,-1,-1,-1],[-1,-1,-1],0],[8899343972,1,0,130,1,23,11779,2311,80,[53,2,-1,-1,57,126],[-1,-1,-1],1],[8899347646,1,0,130,1,15,8838,1651,80,[46,87,5,126,124,57],[31,107,-1],0],[8899348681,1,0,128,0,15,5732,2061,80,[126,65,53,123,103,-1],[-1,-1,-1],0],[8899350361,1,0,129,0,10,3567,1403,80,[5,31,123,112,40,126],[-1,-1,-1],0],[8899353939,1,0,3,0,15,8275,2105,75,[47,53,-1,44,50,38],[-1,-1,-1],1],[8899355291,1,0,3,1,14,9525,1716,80,[57,48,53,-1,-1,-1],[-1,-1,-1],1],[8899356200,1,0,130,1,19,12607,2472,80,[14,57,69,11,124,2],[107,-1,-1],0],[8899365216,1,0,132,1,16,10131,2030,80,[44,11,-1,66,22,5],[107,-1,-1],0],[8899365871,1,0,0,1,19,11417,2018,80,[107,53,57,-1,11,-1],[-1,-1,-1],0],[8899365945,1,0,131,0,10,3302,1446,80,[-1,31,66,126,103,5],[23,38,107],0],[8899367296,1,0,3,0,23,10289,3070,80,[53,48,47,-1,66,-1],[-1,-1,-1],0],[8899367809,1,0,128,0,12,5715,1982,80,[5,66,48,123,79,-1],[-1,-1,-1],0],[8899369558,1,0,4,0,21,12913,2019,80,[16,71,31,86,66,118],[-1,18,-1],1],[8899373911,1,0,130,0,22,10952,2720,74,[66,53,-1,27,1,-1],[-1,-1,-1],1],[8899391056,1,0,3,1,14,10444,1763,80,[53,12,66,48,31,-1],[-1,-1,-1],1],[8899398253,1,0,3,1,20,12160,2265,80,[-1,28,46,11,5,57],[-1,-1,-1],0],[8899398449,1,0,132,1,19,10651,2317,80,[5,57,123,44,-1,2],[-1,-1,-1],1],[8899405228,1,0,132,1,26,20740,3128,80,[57,6,34,11,86,118],[38,-1,-1],0],[8899420074,1,0,0,1,18,11003,2045,80,[57,48,111,-1,5,31],[-1,114,-1],0],[8899420734,1,0,130,1,20,11841,2201,80,[53,12,57,12,-1,12],[114,-1,-1],0],[8899425431,1,0,131,1,18,10012,2182,80,[5,57,11,31,-1,28],[125,-1,-1],0],[8899432358,1,0,129,0,15,8327,2222,80,[5,69,31,48,57,123],[-1,-1,-1],0],[8899434045,1,0,1,0,16,9995,1988,80,[5,57,55,42,69,123],[-1,-1,-1],1],[8899438000,1,0,1,0,15,9773,2091,80,[48,44,123,5,126,31],[66,-1,-1],0],[8899440238,1,0,132,1,26,18889,4393,80,[53,28,34,66,48,44],[-1,-1,-1],1],[8899444481,1,0,4,0,19,7224,2419,80,[31,48,123,57,5,126],[-1,-1,38],0],[8899447787,1,0,128,0,10,5800,1950,80,[66,73,5,85,123,31],[23,112,-1],1],[8899448433,1,0,129,1,13,8145,1560,80,[48,66,53,-1,-1,-1],[-1,-1,-1],1],[8899453104,1,0,1,0,12,5708,1739,80,[14,123,57,-1,31,48],[107,-1,-1],0],[8899454018,1,0,3,1,17,11263,1797,75,[57,48,2,78,-1,5],[-1,-1,-1],1],[8899460632,1,0,2,0,19,10714,2425,80,[53,-1,31,48,123,57],[-1,-1,-1],1],[8899468824,1,0,132,1,23,15213,3304,80,[5,44,48,124,28,-1],[-1,-1,31],0],[8899470476,1,0,3,0,14,5514,2007,75,[66,79,123,126,85,5],[-1,-1,-1],1],[8899477089,1,0,129,1,15,9239,1716,80,[14,-1,36,69,18,57],[-1,-1,-1],0],[8899479249,1,0,129,1,25,14641,3164,80,[-1,83,28,125,5,2],[31,-1,-1],0],[8899503223,1,0,128,1,19,14415,2516,80,[78,57,53,118,123,-1],[-1,-1,107],1],[8899505140,1,0,1,0,18,11569,2539,80,[123,63,47,5,65,11],[31,-1,-1],0],[8899508747,1,0,1,1,15,10140,1618,80,[118,57,5,38,-1,-1],[-1,-1,-1],0],[8899512542,1,0,131,1,15,7791,1623,80,[53,66,79,126,123,81],[-1,-1,-1],1],[8899515366,1,0,2,0,14,5384,1718,80,[87,123,57,-1,-1,5],[-1,-1,-1],0],[8899517437,1,0,0,0,13,6692,1898,80,[57,48,5,126,31,107],[125,-1,-1],0],[8899529607,1,0,2,1,19,10768,2041,80,[-1,57,79,-1,48,53],[-1,-1,-1],0],[8899530207,1,0,131,0,26,15427,3238,75,[11,48,5,104,47,31],[-1,-1,-1],1],[8899530830,1,0,132,0,11,6447,1986,80,[14,57,-1,123,-1,47],[-1,-1,-1],0],[8899531763,1,0,129,1,15,6804,1666,80,[5,65,-1,48,-1,124],[18,-1,107],0],[8899546751,1,0,129,0,14,6203,1994,80,[66,5,31,44,126,102],[103,-1,-1],0],[8899554556,1,0,3,1,19,13781,2333,80,[53,57,83,31,-1,-1],[107,-1,-1],0],[8899555927,1,0,128,1,22,15489,2685,80,[48,53,-1,57,107,2],[-1,38,-1],0],[8899556526,1,0,132,0,13,6738,1749,80,[5,66,48,-1,31,122],[-1,-1,-1],0],[8899559731,1,0,130,0,15,8104,2005,80,[69,123,48,57,5,107],[-1,-1,-1],0],[8899562455,1,0,0,0,16,7535,2172,71,[5,57,61,17,48,124],[-1,-1,-1],1],[8899564527,1,0,1,1,19,12175,2118,80,[57,28,48,-1,5,-1],[-1,-1,107],0],[8899564791,1,0,2,0,16,8190,2208,80,[87,63,44,14,-1,66],[12,-1,-1],1],[8899569584,1,0,129,1,18,13829,1920,80,[70,-1,57,5,11,119],[-1,-1,-1],0],[8899570693,1,0,4,0,22,13653,2467,80,[53,57,48,77,85,-1],[-1,-1,-1],0],[8899572859,1,0,2,1,13,9661,1426,80,[53,57,61,-1,50,3],[107,-1,-1],0],[8899574640,1,0,130,0,12,4438,1814,75,[57,61,-1,-1,123,5],[107,-1,-1],1],[8899575471,1,0,129,0,16,8438,2068,80,[115,55,123,121,66,11],[-1,-1,-1],1],[8899581640,1,0,128,0,21,13303,2409,80,[28,57,123,48,2,5],[32,-1,-1],0],[8899583533,1,0,132,0,12,5215,1572,80,[31,5,124,57,-1,-1],[-1,-1,-1],0],[8899584416,1,0,1,0,15,8730,2179,75,[5,124,-1,69,48,66],[-1,-1,-1],1],[8899584809,1,0,132,0,22,13551,3271,80,[53,57,31,123,11,47],[126,107,-1],0],[8899586091,1,0,0,0,14,5528,1901,80,[103,123,-1,57,-1,5],[-1,-1,-1],0],[8899586429,1,0,132,1,13,8074,1997,80,[82,-1,57,5,12,-1],[107,-1,-1],1],[8899588239,1,0,130,0,24,12847,3112,80,[44,57,123,31,11,5],[69,107,-1],1],[8899589976,1,0,132,1,21,12370,2248,80,[11,48,57,5,31,-1],[-1,-1,-1],0],[8899591629,1,0,131,1,27,18501,3371,75,[48,57,11,108,1,5],[125,-1,114],1],[8899593172,1,0,128,0,14,7376,1788,74,[48,123,69,31,5,66],[27,107,-1],1],[8899595691,1,0,1,1,23,14059,2222,74,[11,48,123,2,5,47],[-1,66,107],1],[8899603955,1,0,129,1,19,12350,2221,80,[57,44,28,23,5,123],[107,38,-1],0],[8899607153,1,0,0,1,16,12220,1851,80,[48,5,57,-1,-1,44],[-1,-1,-1],0],[8899610564,1,0,131,0,16,9446,2219,80,[44,53,66,107,17,124],[-1,-1,-1],0],[8899612202,1,0,1,0,12,4976,1745,80,[18,69,125,65,20,98],[18,18,-1],0],[8899618842,1,0,129,1,16,10280,1900,80,[2,46,5,48,-1,66],[-1,-1,-1],0],[8899624702,1,0,0,0,27,15909,4499,80,[53,11,57,123,48,1],[107,-1,-1],0],[8899624875,1,0,130,1,18,11704,1860,80,[57,126,48,-1,5,-1],[-1,-1,107],0],[8899626695,1,0,132,1,18,11169,1933,80,[57,53,124,2,31,87],[38,-1,-1],0],[8899627403,1,0,0,0,24,18433,3456,80,[44,46,48,57,53,1],[-1,-1,-1],0],[8899627555,1,0,4,0,15,5924,2358,74,[123,69,34,66,5,-1],[-1,-1,-1],1],[8899628471,1,0,128,1,20,12621,1991,80,[57,2,11,-1,5,47],[-1,-1,107],0],[8899629236,1,0,2,1,23,17779,3284,80,[53,57,76,48,-1,-1],[-1,87,-1],1],[8899635990,1,0,4,1,14,8239,1548,80,[79,-1,5,18,18,83],[-1,-1,-1],1],[8899638755,1,0,2,0,17,7794,2256,80,[5,48,31,107,-1,69],[38,-1,-1],0],[8899643232,1,0,129,0,13,5215,1691,80,[5,32,66,84,81,-1],[94,-1,-1],0],[8899644458,1,0,1,1,16,9949,1841,74,[48,123,69,-1,5,57],[-1,-1,-1],1],[8899646613,1,0,3,1,18,10359,2008,80,[53,57,31,2,36,32],[-1,-1,-1],0],[8899646727,1,0,129,0,16,9945,1983,80,[66,124,2,48,44,5],[107,-1,-1],1],[8899650175,1,0,131,1,17,10371,1966,80,[69,124,44,5,57,31],[107,-1,-1],1],[8899651770,1,0,129,0,17,7310,2134,80,[57,5,123,33,-1,120],[-1,-1,-1],1],[8899655131,1,0,4,0,17,10478,2424,80,[5,48,57,47,2,107],[-1,-1,-1],0],[8899658344,1,0,2,1,18,9839,1984,80,[57,53,-1,-1,-1,-1],[-1,-1,-1],1],[8899662013,1,0,129,1,19,11682,2086,80,[-1,2,57,53,31,126],[-1,-1,-1],0],[8899671284,1,0,1,1,16,8852,1894,80,[53,66,48,-1,-1,-1],[-1,-1,-1],0],[8899673845,1,0,132,1,25,13572,3272,80,[57,53,47,-1,11,123],[52,-1,-1],0],[8899678548,1,0,130,1,23,15169,2424,80,[5,46,11,121,57,2],[126,47,107],0],[8899683753,1,0,2,1,14,8971,1507,80,[5,57,-1,107,-1,48],[-1,-1,-1],0],[8899685548,1,0,131,1,16,11355,1950,80,[53,66,48,27,-1,-1],[-1,107,-1],1],[8899686811,1,0,132,0,18,9591,2528,80,[44,48,5,66,31,-1],[-1,-1,-1],0],[8899690813,1,0,3,0,20,11803,2637,80,[57,48,-1,-1,123,53],[-1,107,-1],0],[8899694249,1,0,1,0,27,12280,3748,75,[123,34,48,5,2,11],[31,38,-1],1],[8899705144,1,0,3,1,25,17432,3116,80,[48,53,57,-1,2,85],[107,-1,-1],0],[8899709624,1,0,4,1,15,7732,1625,80,[5,57,125,28,-1,-1],[-1,-1,-1],0],[8899714767,1,0,1,0,13,5390,1843,80,[31,5,2,40,-1,65],[-1,-1,-1],0],[8899716313,1,0,132,1,18,10314,1944,80,[48,57,53,-1,-1,-1],[-1,107,-1],0],[8899716700,1,0,2,0,17,8133,2132,80,[1,5,57,107,129,-1],[-1,-1,-1],0],[8899718166,1,0,4,1,15,9852,2232,80,[28,124,57,69,5,107],[38,-1,-1],0],[8899719470,1,0,1,1,21,16156,2216,80,[44,48,66,125,53,11],[107,126,-1],0],[8899724163,1,0,128,0,11,5981,1909,80,[5,123,57,114,31,40],[107,-1,-1],0],[8899726008,1,0,129,0,16,6721,1946,73,[5,57,2,31,123,-1],[107,-1,-1],1],[8899728553,1,0,130,1,20,11282,2092,74,[66,123,53,2,11,107],[-1,-1,-1],1],[8899739222,1,0,128,0,24,12459,3210,74,[-1,5,31,48,63,123],[107,-1,-1],1],[8899739860,1,0,1,1,18,13036,2150,80,[53,57,-1,109,-1,126],[-1,-1,-1],0],[8899741788,1,0,130,0,18,11656,2480,80,[53,31,44,123,12,57],[-1,-1,-1],0],[8899745128,1,0,128,0,12,5124,1744,80,[66,5,69,61,27,126],[-1,-1,-1],0],[8899745499,1,0,128,1,14,7675,1540,80,[66,70,-1,31,14,111],[-1,-1,-1],0],[8899745948,1,0,132,0,13,4539,2031,80,[12,-1,5,69,12,66],[123,-1,-1],0],[8899749287,1,0,131,1,20,10127,2031,80,[57,53,125,31,52,-1],[-1,-1,-1],0],[8899762361,1,0,2,0,15,5518,1883,80,[5,66,125,48,61,27],[-1,-1,-1],0],[8899770292,1,0,3,0,26,14708,3302,75,[76,123,52,11,57,53],[31,-1,-1],1],[8899770909,1,0,4,1,17,9704,1951,80,[53,48,-1,66,-1,-1],[-1,-1,-1],1],[8899771417,1,0,129,0,20,7049,2389,80,[53,-1,31,-1,66,107],[-1,-1,-1],1],[8899771775,1,0,129,0,15,7890,1998,73,[5,57,112,48,31,126],[107,-1,-1],1],[8899778240,1,0,0,1,21,17239,2573,75,[48,53,57,118,-1,2],[-1,-1,-1],1],[8899779404,1,0,4,1,18,9178,1750,80,[-1,57,31,5,69,2],[-1,-1,-1],0],[8899781498,1,0,129,1,23,11675,2487,80,[5,107,-1,63,57,123],[38,-1,-1],1],[8899784919,1,0,1,1,20,12881,2615,80,[11,53,57,82,-1,-1],[-1,-1,-1],0],[8899785935,1,0,132,0,19,9180,2472,80,[57,48,-1,53,-1,123],[-1,-1,-1],1],[8899786228,1,0,3,0,14,5496,1937,80,[126,5,31,57,-1,-1],[-1,-1,-1],0],[8899786925,1,0,128,1,22,15538,2488,80,[2,123,53,108,-1,57],[-1,-1,-1],0],[8899787778,1,0,0,1,16,7423,1841,80,[87,69,57,-1,-1,5],[-1,-1,-1],0],[8899788296,1,0,130,1,14,8824,1544,80,[-1,-1,-1,61,57,53],[-1,-1,-1],1],[8899796570,1,0,129,0,16,8182,2045,80,[63,-1,5,124,47,66],[107,126,-1],0],[8899797620,1,0,3,1,16,8782,1912,80,[66,5,125,48,79,2],[107,12,-1],0],[8899799347,1,0,4,0,20,9203,2352,80,[48,5,44,57,-1,56],[107,-1,-1],0],[8899805953,1,0,0,1,14,9158,1739,80,[5,122,48,124,31,57],[-1,33,-1],0],[8899811637,1,0,128,0,27,13921,3702,80,[57,44,-1,53,-1,1],[31,107,-1],1],[8899815908,1,0,128,0,16,8897,2269,80,[123,53,-1,48,66,-1],[-1,-1,-1],1],[8899816238,1,0,4,0,12,5554,1666,80,[48,66,5,27,40,124],[-1,-1,-1],0],[8899816281,1,0,131,0,16,8657,2367,80,[1,14,124,11,46,66],[126,87,31],0],[8899818971,1,0,131,0,16,10091,2147,80,[66,-1,5,125,28,48],[-1,-1,-1],1],[8899819703,1,0,2,0,14,7820,1872,80,[48,5,65,123,38,2],[107,-1,-1],0],[8899820760,1,0,128,0,9,3663,1185,80,[87,5,66,114,-1,-1],[-1,-1,-1],0],[8899823328,1,0,128,0,21,8981,2668,75,[48,57,47,31,5,124],[107,-1,38],1],[8899834500,1,0,0,1,17,12863,2219,80,[44,57,48,123,5,126],[107,31,-1],1],[8899840369,1,0,132,1,22,11108,2355,80,[11,5,48,2,-1,66],[-1,-1,-1],1],[8899840473,1,0,1,1,14,8709,1807,80,[53,66,61,79,123,27],[-1,-1,-1],1],[8899852124,1,0,131,1,19,14197,2272,72,[53,1,118,57,-1,-1],[107,-1,-1],1],[8899857019,1,0,132,1,20,13905,2307,80,[48,57,53,50,33,38],[107,-1,-1],0],[8899857861,1,0,0,1,15,8768,1686,80,[69,57,48,-1,5,126],[-1,-1,-1],1],[8899864893,1,0,129,1,18,10659,2084,80,[28,124,31,57,-1,53],[-1,-1,-1],0],[8899865699,1,0,128,0,18,10498,2208,80,[-1,53,48,107,124,66],[-1,-1,-1],1],[8899865763,1,0,128,1,26,14018,3562,80,[2,44,11,47,48,5],[-1,-1,-1],0],[8899865801,1,0,129,0,19,9092,2118,80,[48,57,47,5,123,23],[107,-1,-1],1],[8899866781,1,0,2,0,20,9457,2253,80,[53,57,-1,-1,126,123],[-1,-1,-1],0],[8899868583,1,0,132,0,21,12949,2937,80,[5,69,48,104,123,31],[-1,107,-1],1],[8899869996,1,0,0,0,19,10843,2432,80,[66,83,48,2,-1,5],[-1,-1,-1],0],[8899871890,1,0,2,1,25,24033,2791,80,[113,86,55,29,6,58],[-1,-1,-1],1],[8899875340,1,0,128,1,26,18669,3234,80,[5,48,11,63,46,31],[38,1,107],0],[8899876068,1,0,128,1,11,6277,1249,80,[78,11,12,66,123,5],[-1,-1,-1],0],[8899883760,1,0,128,0,13,5855,1714,80,[124,57,5,-1,126,107],[-1,-1,-1],1],[8899885708,1,0,1,0,12,5475,1731,80,[5,31,123,-1,-1,57],[-1,-1,-1],0],[8899890333,1,0,131,0,18,13166,2517,80,[5,31,57,48,107,-1],[-1,22,-1],0],[8899892903,1,0,3,0,13,6325,1759,80,[53,31,-1,79,-1,65],[107,-1,-1],0],[8899892953,1,0,2,0,17,8476,2500,75,[5,48,-1,126,57,-1],[-1,-1,-1],1],[8899894028,1,0,4,1,17,13414,1998,80,[5,66,85,77,55,76],[112,-1,107],0],[8899897097,1,0,131,0,10,5395,1510,80,[66,119,12,5,123,40],[69,32,-1],0],[8899899827,1,0,128,0,17,10527,2612,80,[31,44,53,57,17,-1],[-1,-1,-1],0],[8899900868,1,0,0,0,19,8072,2216,80,[111,5,48,65,107,125],[-1,-1,-1],1],[8899903100,1,0,131,1,11,5961,1303,80,[31,57,123,5,56,20],[107,-1,-1],0],[8899905764,1,0,128,0,16,8703,2289,80,[66,63,123,69,5,87],[-1,-1,-1],1],[8899907647,1,0,129,1,21,14478,2284,80,[11,44,57,53,48,-1],[-1,-1,-1],1],[8899908830,1,0,130,1,17,12706,1873,80,[53,107,57,31,125,11],[-1,-1,-1],1],[8899912209,1,0,0,1,23,15427,3281,80,[48,44,46,57,123,53],[38,-1,-1],0],[8899913442,1,0,129,1,16,10297,1983,80,[-1,82,57,84,33,5],[107,-1,-1],0],[8899915773,1,0,130,0,15,7409,2075,80,[65,108,48,123,107,14],[-1,-1,-1],0],[8899921429,1,0,128,1,19,10806,2246,80,[2,66,48,-1,-1,5],[-1,-1,-1],1],[8899924298,1,0,1,1,13,7846,1736,80,[5,57,69,125,107,-1],[-1,-1,-1],1],[8899924409,1,0,132,1,25,15949,2665,80,[47,11,57,31,53,10],[-1,-1,107],1],[8899926228,1,0,0,0,15,7791,2131,80,[53,57,125,-1,-1,-1],[-1,-1,-1],1],[8899927595,1,0,129,1,15,10732,1591,80,[70,57,53,-1,125,12],[107,-1,-1],1],[8899928208,1,0,1,1,16,8613,1594,80,[126,66,53,23,123,48],[-1,-1,-1],1],[8899935509,1,0,0,0,19,11371,2541,80,[44,53,57,-1,-1,2],[-1,-1,-1],0],[8899939548,1,0,129,0,16,9713,2272,80,[57,48,53,-1,123,31],[-1,-1,-1],0],[8899941090,1,0,128,0,11,4461,1502,80,[5,44,32,38,66,-1],[-1,-1,-1],1],[8899941905,1,0,3,1,15,9380,2061,80,[53,125,31,57,103,87],[93,-1,-1],1],[8899941983,1,0,132,0,17,8749,2298,80,[115,48,119,-1,2,121],[-1,-1,-1],1],[8899951596,1,0,2,0,15,6229,1839,80,[5,48,57,125,41,-1],[-1,107,-1],0],[8899955745,1,0,4,1,11,7799,1323,75,[19,53,57,-1,-1,-1],[-1,107,-1],1],[8899957503,1,0,132,1,15,10601,1822,80,[2,57,5,12,48,107],[-1,-1,-1],0],[8899957831,1,0,131,0,15,8223,1982,80,[5,31,107,48,123,57],[-1,-1,-1],1],[8899958462,1,0,129,0,16,9349,2094,80,[57,48,125,5,1,38],[39,-1,-1],0],[8899963421,1,0,0,1,21,15526,2346,80,[15,28,108,124,66,-1],[-1,-1,-1],1],[8899967328,1,0,0,0,20,9499,3193,80,[5,66,125,48,27,1],[-1,31,-1],1],[8899973289,1,0,128,1,20,13511,2274,74,[63,34,5,124,57,48],[-1,-1,-1],1],[8899976725,1,0,130,0,14,5223,1916,80,[5,57,40,126,-1,31],[-1,-1,-1],0],[8899977321,1,0,0,1,20,13075,2287,75,[1,57,53,124,-1,-1],[-1,-1,-1],1],[8899979069,1,0,128,0,14,5708,1880,80,[5,31,56,125,66,44],[-1,-1,-1],1],[8899980958,1,0,4,0,17,7277,2469,80,[69,44,5,126,31,123],[-1,-1,-1],1],[8899981465,1,0,0,1,18,9550,1659,80,[48,5,57,107,69,123],[-1,-1,-1],1],[8899984648,1,0,132,0,13,6812,2048,80,[125,57,107,5,22,69],[-1,-1,-1],0],[8899985433,1,0,132,1,22,12646,2906,80,[123,44,53,-1,57,-1],[-1,126,-1],0],[8899987842,1,0,131,1,17,10148,1703,80,[57,5,69,125,107,44],[-1,-1,-1],1],[8899990017,1,0,4,0,20,8587,2397,80,[57,63,-1,5,-1,-1],[-1,-1,-1],1],[8899991967,1,0,3,0,17,7532,2200,80,[123,61,57,31,44,5],[-1,-1,-1],0],[8899992247,1,0,129,0,13,5381,1970,75,[5,69,123,27,32,66],[107,-1,-1],1],[8899995124,1,0,132,1,18,10817,2522,75,[48,111,44,14,125,31],[107,-1,-1],1],[8900006493,1,0,0,0,13,5604,1745,80,[5,28,-1,65,-1,-1],[-1,-1,-1],1],[8900007424,1,0,4,0,13,7019,1890,80,[5,48,57,-1,125,41],[124,-1,-1],0],[8900012836,1,0,3,0,19,11214,2600,80,[31,63,53,48,52,50],[-1,-1,-1],0],[8900017877,1,0,131,0,14,7381,1891,80,[53,61,79,-1,119,123],[-1,-1,-1],1],[8900020159,1,0,1,0,18,11959,2382,80,[5,48,47,2,77,57],[-1,-1,-1],1],[8900020229,1,0,1,0,25,16614,3775,80,[77,63,44,1,48,2],[9,112,124],1],[8900022596,1,0,129,1,22,9130,2481,80,[48,5,66,11,-1,124],[23,107,-1],0],[8900034711,2,0,2,1,16,10474,1896,80,[-1,57,53,-1,123,-1],[-1,-1,-1],0],[8900034743,2,0,130,0,13,5604,1593,80,[5,48,66,27,123,31],[41,107,-1],0],[8900034760,2,0,131,0,10,4757,1477,80,[5,57,-1,114,10,36],[-1,-1,-1],1],[8900050413,2,0,2,0,14,5485,1574,80,[38,57,31,36,123,5],[-1,-1,-1],0],[8900050982,2,0,4,1,15,8069,1607,80,[53,48,123,-1,101,12],[-1,-1,107],0],[8900055230,2,0,131,0,18,10435,1980,80,[-1,48,123,57,53,107],[-1,-1,-1],0],[8900055797,2,0,128,1,23,12046,2534,80,[108,57,123,48,5,-1],[-1,-1,-1],0],[8900056608,2,0,128,0,13,7959,1575,80,[57,5,48,123,-1,-1],[-1,-1,107],0],[8900056987,2,0,129,1,21,12172,2342,80,[57,123,5,48,2,69],[107,23,-1],0],[8900059264,2,0,3,0,10,4561,1550,80,[123,48,66,-1,5,-1],[-1,-1,-1],0],[8900059309,2,0,130,1,26,18044,2898,80,[53,48,26,66,-1,-1],[-1,-1,-1],1],[8900060603,2,0,132,0,16,8466,1857,80,[-1,57,53,123,107,23],[-1,-1,-1],0],[8900082558,2,0,130,1,19,13490,2220,80,[125,63,57,87,53,126],[-1,-1,-1],0],[8900084060,2,0,3,0,19,11872,2356,80,[5,47,110,31,44,122],[107,126,-1],0],[8900086436,2,0,132,0,21,12730,2539,80,[11,31,53,57,123,2],[-1,-1,-1],0],[8900086948,2,0,132,1,21,11286,2203,75,[53,48,44,126,-1,65],[107,114,-1],1],[8900088787,2,0,130,1,16,11220,1847,80,[69,126,38,57,5,11],[107,-1,-1],0],[8900089764,2,0,3,1,19,14401,2476,80,[31,28,48,2,5,-1],[-1,-1,-1],0],[8900090601,2,0,3,0,11,5451,1828,74,[78,123,57,5,107,-1],[-1,-1,-1],1],[8900091241,2,0,4,0,14,8661,1991,80,[57,10,-1,53,-1,-1],[-1,107,-1],0],[8900095132,2,0,4,1,13,7589,1381,80,[31,-1,99,57,5,-1],[107,-1,-1],1],[8900096132,2,0,128,0,15,7496,2300,80,[123,48,65,11,5,31],[107,38,12],0],[8900105709,2,0,130,1,17,10209,1664,80,[28,48,57,5,87,-1],[107,-1,-1],0],[8900111444,2,0,3,1,21,12929,2459,80,[46,1,5,47,65,69],[107,123,-1],0],[8900122126,2,0,2,0,14,8182,1883,80,[48,47,2,-1,31,5],[-1,-1,-1],1],[8900124324,2,0,0,0,27,16304,3631,75,[44,53,-1,2,17,-1],[-1,66,-1],1],[8900134406,2,0,4,0,17,9863,1942,80,[48,1,44,73,126,14],[50,-1,-1],0],[8900139142,2,0,130,1,20,11102,2401,75,[57,73,46,53,-1,25],[-1,-1,-1],1],[8900139693,2,0,2,0,19,11152,2454,80,[5,47,124,28,48,2],[107,-1,-1],0],[8900141701,2,0,3,1,23,13057,2776,80,[124,66,46,47,53,28],[-1,-1,-1],0],[8900141993,2,0,1,0,11,4480,1412,80,[5,66,69,107,32,125],[-1,-1,-1],1],[8900146339,2,0,3,1,18,9684,1926,80,[5,57,31,48,124,56],[114,36,20],0],[8900148503,2,0,131,1,22,11287,2821,75,[15,65,124,69,31,5],[23,-1,-1],1],[8900156072,2,0,132,1,22,14078,2694,80,[-1,53,31,57,48,63],[-1,38,-1],1],[8900158436,2,0,129,0,27,21049,3694,80,[11,-1,63,104,44,53],[31,-1,-1],1],[8900159422,2,0,129,0,11,5880,1668,80,[66,123,5,31,44,-1],[107,-1,-1],0],[8900166817,2,0,0,0,20,8710,2349,80,[126,2,115,73,73,73],[-1,-1,-1],0],[8900171663,2,0,0,0,15,10629,2006,80,[108,1,44,73,56,14],[107,31,20],1],[8900177605,2,0,132,1,25,13706,2874,80,[53,57,123,52,-1,118],[107,-1,-1],0],[8900178937,2,0,130,0,11,4944,1920,80,[65,125,44,5,129,-1],[-1,-1,-1],0],[8900180749,2,0,2,0,21,8659,2800,80,[11,102,126,66,53,31],[123,-1,-1],0],[8900186194,2,0,3,0,14,11347,2220,80,[44,57,53,36,38,79],[-1,-1,-1],1],[8900188441,2,0,128,0,18,8658,2300,80,[53,102,57,41,124,103],[-1,-1,-1],1],[8900188560,2,0,2,0,20,17659,2507,80,[57,28,76,11,14,118],[31,-1,-1],0],[8900192006,2,0,3,0,19,11113,2585,80,[57,61,53,48,-1,-1],[107,-1,-1],1],[8900193023,2,0,1,0,30,34011,4065,80,[59,76,113,86,106,64],[52,38,52],0],[8900196869,2,0,129,1,19,13942,2148,80,[47,53,48,123,57,40],[-1,-1,-1],1],[8900199232,2,0,131,0,17,11898,2128,80,[48,69,47,73,1,14],[126,-1,-1],0],[8900206930,2,0,129,1,30,32759,5027,80,[44,11,127,2,76,53],[125,-1,-1],1],[8900211731,2,0,129,1,20,10148,2047,80,[57,124,5,31,44,-1],[107,-1,-1],1],[8900213289,2,0,129,0,19,8828,2751,80,[123,57,47,28,5,107],[-1,-1,-1],0],[8900213820,2,0,0,0,16,9483,2178,80,[-1,28,80,125,57,14],[-1,-1,-1],0],[8900214109,2,0,132,1,26,16437,3107,80,[53,1,12,57,46,124],[107,-1,-1],1],[8900219106,2,0,132,1,20,13011,2186,80,[5,63,48,57,-1,-1],[-1,-1,-1],0],[8900223028,2,0,0,0,18,9525,2160,80,[123,57,48,5,85,79],[50,-1,112],1],[8900224429,2,0,131,0,14,6002,1735,80,[48,-1,69,5,123,65],[-1,-1,-1],0],[8900229605,2,0,132,0,23,16873,2880,80,[108,53,48,123,73,1],[-1,-1,-1],0],[8900241722,2,0,128,1,19,10645,1967,74,[11,126,57,-1,-1,53],[-1,-1,-1],1]]}